fast-galaxy/__init__.py
fast-galaxy/__main__.py
fast-galaxy/fast_galaxy.py
fast_galaxy/__init__.py
fast_galaxy/__main__.py
fast_galaxy/fast_galaxy.py
fast_galaxy-0.1.3.dist-info/LICENSE
fast_galaxy-0.1.3.dist-info/METADATA
fast_galaxy-0.1.3.dist-info/WHEEL
fast_galaxy-0.1.3.dist-info/entry_points.txt
fast_galaxy-0.1.3.dist-info/top_level.txt
fast_galaxy-0.1.3.dist-info/RECORD
