Metadata-Version: 2.1
Name: fast-galaxy
Version: 0.1.3
Summary: A package to split and install Ansible Galaxy requirements in parallel.
Home-page: https://github.com/michael-todorovic/fast-galaxy
Author: Michael Todorovic
Author-email: michael.todorovic@outlook.com
Classifier: Programming Language :: Python :: 3
Classifier: Operating System :: OS Independent
Requires-Python: >=3.6
License-File: LICENSE
Requires-Dist: PyYAML
